{
  "parent": "croparia:croparia/croparia4",
  "criteria": {
    "croparia5": {
      "conditions": {
        "items": [
          {
            "items": [
              "croparia:croparia5"
            ]
          }
        ]
      },
      "trigger": "minecraft:inventory_changed"
    }
  },
  "display": {
    "announce_to_chat": true,
    "description": {
      "translate": "advancements.croparia.croparia5.description"
    },
    "frame": "task",
    "hidden": false,
    "icon": {
      "id": "croparia:croparia5"
    },
    "show_toast": true,
    "title": {
      "translate": "advancements.croparia.croparia5.title"
    }
  },
  "requirements": [
    [
      "croparia5"
    ]
  ],
  "sends_telemetry_event": true
}